LICENSE
README.md
setup.py
code_eval_score/__init__.py
code_eval_score/demo.py
code_eval_score/genscore.py
code_eval_score/matchscore.py
code_eval_score/utils.py
code_eval_score.egg-info/PKG-INFO
code_eval_score.egg-info/SOURCES.txt
code_eval_score.egg-info/dependency_links.txt
code_eval_score.egg-info/requires.txt
code_eval_score.egg-info/top_level.txt