Metadata-Version: 2.1
Name: code-eval-score
Version: 0.2.0
Summary: Automated evaluation of generated code based on CodeBERT and CodeT5.
Home-page: https://github.com/Lizhmq/code-eval-score
Author: Zhuo Li
Author-email: lizhmq@pku.edu.cn
License: MIT
Classifier: License :: OSI Approved :: MIT License
Classifier: Programming Language :: Python
Classifier: Programming Language :: Python :: 3
Classifier: Programming Language :: Python :: 3.6
Classifier: Programming Language :: Python :: Implementation :: CPython
Classifier: Programming Language :: Python :: Implementation :: PyPy
Requires-Python: >=3.6.0
License-File: LICENSE
